chaos_game/main.py
chaos_game/toolchain/option_utils.py
chaos_game/toolchain/plotting_utils.py
chaos_game_engine-0.1.0.dist-info/LICENSE
chaos_game_engine-0.1.0.dist-info/WHEEL
chaos_game_engine-0.1.0.dist-info/METADATA
chaos_game_engine-0.1.0.dist-info/RECORD
