Metadata-Version: 2.1
Name: chaos-game-engine
Version: 0.1.0
Summary: A parameterized exploration of the 'chaos game'.
Home-page: https://github.com/anthonybench/chaos-game
License: GNU GPL
Keywords: non-linear-dynamics,chaos,fractals,random-walk
Author: anthonybench
Author-email: anthonybenchyep@gmail.com
Requires-Python: >=3.10,<4.0
Classifier: License :: Other/Proprietary License
Classifier: Programming Language :: Python :: 3
Classifier: Programming Language :: Python :: 3.10
Project-URL: Repository, https://github.com/anthonybench/chaos-game
